ptutils/__init__.py
ptutils/caching.py
ptutils/debug.py
ptutils/encoding.py
ptutils/file.py
ptutils/globbing.py
ptutils/hashing.py
ptutils/introspection.py
ptutils/io.py
ptutils/lazy.py
ptutils/logging.py
ptutils/numerical.py
ptutils/program.py
ptutils/punning.py
ptutils/regex.py
ptutils/text.py
ptutils/time.py
ptutils/typing.py
ptutils/uid.py
ptutils/undefined.py
ptutils/version.py
ptutils/cli/__init__.py
ptutils/cli/simple.py
ptutils-1.1.4.dist-info/AUTHORS
ptutils-1.1.4.dist-info/LICENSE.txt
ptutils-1.1.4.dist-info/METADATA
ptutils-1.1.4.dist-info/WHEEL
ptutils-1.1.4.dist-info/pbr.json
ptutils-1.1.4.dist-info/top_level.txt
ptutils-1.1.4.dist-info/RECORD
