Metadata-Version: 2.1
Name: ptutils
Version: 1.1.4
Summary: A repository of oft used functions and utility classes.
Home-page: https://www.principledtechnologies.com
Author: Christopher Wolfe
Author-email: cwolfe@principledtechnologies.com
License: Proprietary
Project-URL: Documentation, https://principled.technologies.gitlab.io/community/ptutils
Project-URL: Bug Tracker, https://gitlab.com/principled.technologies/community/ptutils/issues
Classifier: Programming Language :: Python :: 3
Classifier: Development Status :: 4 - Beta
Classifier: Environment :: Console
Classifier: Intended Audience :: Developers
Classifier: Intended Audience :: Information Technology
Classifier: License :: Other/Proprietary License
Classifier: Operating System :: OS Independent
Requires-Python: >=3.6
License-File: LICENSE.txt
License-File: AUTHORS
